storage_remote/__init__.py
storage_remote/remote_storage.py
storage_remote-0.0.9.dist-info/METADATA
storage_remote-0.0.9.dist-info/WHEEL
storage_remote-0.0.9.dist-info/top_level.txt
storage_remote-0.0.9.dist-info/RECORD
