Metadata-Version: 2.1
Name: storage-remote
Version: 0.0.9
Home-page: https://github.com/circles-zone/storage-remote-graphql-python-package
Author: Circles
Author-email: info@circles.life
Classifier: Programming Language :: Python :: 3
Classifier: License :: Other/Proprietary License
Classifier: Operating System :: OS Independent
Requires-Dist: requests >=2.31.0
Requires-Dist: python-sdk-remote >=0.0.93
Requires-Dist: url-remote >=0.0.28
